{
  "service": "GOV.UK",
  "slug": "gov-uk",
  "datetime": "2015-10-20T18:09:45.797Z",
  "journeys": [
    {
      "name": "Browse",
      "slug": "browse",
      "screens": [
        {
          "slug": "home",
          "image-path": "screenshots/GOV.UK/Browse/1024-full/01-home.png",
          "image-filename": "01-home.png"
        },
        {
          "slug": "browse",
          "image-path": "screenshots/GOV.UK/Browse/1024-full/02-browse.png",
          "image-filename": "02-browse.png"
        }
      ]
    }
  ]
}